yaml2args/__init__.py
yaml2args/tools.py
yaml2args-0.0.2.dist-info/LICENSE
yaml2args-0.0.2.dist-info/METADATA
yaml2args-0.0.2.dist-info/WHEEL
yaml2args-0.0.2.dist-info/top_level.txt
yaml2args-0.0.2.dist-info/RECORD
